imtec_workflow/__init__.py
imtec_workflow-0.1.1.dist-info/METADATA
imtec_workflow-0.1.1.dist-info/WHEEL
imtec_workflow-0.1.1.dist-info/entry_points.txt
imtec_workflow-0.1.1.dist-info/RECORD
